chunkr/__init__.py
chunkr/chunk_dir.py
chunkr/chunker.py
chunkr/exceptions.py
chunkr/py.typed
chunkr-0.3.1.dist-info/LICENSE
chunkr-0.3.1.dist-info/WHEEL
chunkr-0.3.1.dist-info/METADATA
chunkr-0.3.1.dist-info/RECORD
