Metadata-Version: 2.1
Name: chunkr
Version: 0.3.1
Summary: A library for chunking different types of data files.
Home-page: https://github.com/1b5d/chunkr
License: MIT
Author: 1b5d
Author-email: 8110504+1b5d@users.noreply.github.com
Requires-Python: >=3.8,<4.0
Classifier: License :: OSI Approved :: MIT License
Classifier: Programming Language :: Python :: 3
Classifier: Programming Language :: Python :: 3.8
Classifier: Programming Language :: Python :: 3.9
Classifier: Programming Language :: Python :: 3.10
Classifier: Programming Language :: Python :: 3.11
Requires-Dist: fsspec (>=2022.7.1,<2023.0.0)
Requires-Dist: paramiko (>=2.11.0,<3.0.0)
Requires-Dist: pyarrow (>=11.0.0,<12.0.0)
Project-URL: Repository, https://github.com/1b5d/chunkr
